README
setup.py
pyextend/__init__.py
pyextend.egg-info/PKG-INFO
pyextend.egg-info/SOURCES.txt
pyextend.egg-info/dependency_links.txt
pyextend.egg-info/top_level.txt
pyextend.egg-info/zip-safe
pyextend/core/__init__.py
pyextend/core/fieldref.py
pyextend/core/itertools.py
pyextend/core/log.py
pyextend/core/math.py
pyextend/core/wrappers/__init__.py
pyextend/core/wrappers/accepts.py
pyextend/core/wrappers/singleton.py
pyextend/core/wrappers/system.py
pyextend/core/wrappers/timeout.py
pyextend/core/wrappers/timethis.py
pyextend/formula/__init__.py
pyextend/formula/lbstools.py
pyextend/network/__init__.py
pyextend/network/encoding.py
pyextend/network/gziphandler.py
pyextend/network/regex.py
tests/__init__.py
tests/test_core_fieldref.py
tests/test_core_itertools.py
tests/test_core_math.py
tests/test_core_wrappers_accepts.py
tests/test_core_wrappers_singleton.py
tests/test_core_wrappers_system.py
tests/test_core_wrappers_timeout.py
tests/test_formula_lbstools.py
tests/test_network_encoding.py
tests/test_test.py