Metadata-Version: 1.1
Name: pyextend
Version: 0.1.24
Summary: the python extend lib
Home-page: https://github.com/Vito2015/pyextend.git
Author: Vito
Author-email: vito2015@live.com
License: GNU
Download-URL: https://github.com/Vito2015/pyextend.git
Keywords: python extension package
Platform: any
Classifier: Development Status :: 4 - Beta
Classifier: Intended Audience :: Developers
Classifier: License :: OSI Approved :: GNU General Public License v2 or later (GPLv2+)
Classifier: Operating System :: OS Independent
Classifier: Programming Language :: Python
Classifier: Topic :: Software Development :: Libraries
